<?xml version="1.0" encoding="UTF-8"?>
<Tokens version="1.0">
	<File path="Classes/ProjectFileList.html">
		
		<Token>
			<TokenIdentifier>//apple_ref/occ/cl/ProjectFileList</TokenIdentifier>
			<Abstract type="html">A ProjectFileList represents an array controller for a list of files downloaded by a Project.</Abstract>
			<DeclaredIn>ProjectFileList.h</DeclaredIn>
            
			
			<NodeRef refid="35"/>
		</Token>
		
		
		<Token>
			<TokenIdentifier>//apple_ref/occ/instm/ProjectFileList/setStatus:</TokenIdentifier>
			<Abstract type="html">Gives the status of the file list.</Abstract>
			<DeclaredIn>ProjectFileList.h</DeclaredIn>
			
			<Declaration>@property (nonatomic, readonly) NSString *status</Declaration>
			
			
			<Anchor>//api/name/status</Anchor>
            <NodeRef refid="35"/>
		</Token>
		
		<Token>
			<TokenIdentifier>//apple_ref/occ/instm/ProjectFileList/status</TokenIdentifier>
			<Abstract type="html">Gives the status of the file list.</Abstract>
			<DeclaredIn>ProjectFileList.h</DeclaredIn>
			
			<Declaration>@property (nonatomic, readonly) NSString *status</Declaration>
			
			
			<Anchor>//api/name/status</Anchor>
            <NodeRef refid="35"/>
		</Token>
		
		<Token>
			<TokenIdentifier>//apple_ref/occ/instp/ProjectFileList/status</TokenIdentifier>
			<Abstract type="html">Gives the status of the file list.</Abstract>
			<DeclaredIn>ProjectFileList.h</DeclaredIn>
			
			<Declaration>@property (nonatomic, readonly) NSString *status</Declaration>
			
			
			<Anchor>//api/name/status</Anchor>
            <NodeRef refid="35"/>
		</Token>
		
		<Token>
			<TokenIdentifier>//apple_ref/occ/instm/ProjectFileList/count</TokenIdentifier>
			<Abstract type="html">Returns the size of this file list.</Abstract>
			<DeclaredIn>ProjectFileList.h</DeclaredIn>
			
			<Declaration>- (NSUInteger)count</Declaration>
			
			<ReturnValue><Abstract type="html">The number of files this list keeps track of.</Abstract></ReturnValue>
			<Anchor>//api/name/count</Anchor>
            <NodeRef refid="35"/>
		</Token>
		
		<Token>
			<TokenIdentifier>//apple_ref/occ/instm/ProjectFileList/clearFileList</TokenIdentifier>
			<Abstract type="html">Remove all files in this list.</Abstract>
			<DeclaredIn>ProjectFileList.h</DeclaredIn>
			
			<Declaration>- (void)clearFileList</Declaration>
			
			
			<Anchor>//api/name/clearFileList</Anchor>
            <NodeRef refid="35"/>
		</Token>
		
        
        
	</File>
</Tokens>